[
	{
		"tendantoc": "Kinh"
	},
	{
		"tendantoc": "Tày"
	},
	{
		"tendantoc": "Thái"
	},
	{
		"tendantoc": "Hoa"
	},
	{
		"tendantoc": "Khơ-me"
	},
	{
		"tendantoc": "Mường"
	},
	{
		"tendantoc": "Nùng"
	},
	{
		"tendantoc": "HMông"
	},
	{
		"tendantoc": "Dao"
	},
	{
		"tendantoc": "Gia-rai"
	},
	{
		"tendantoc": "Ngái"
	},
	{
		"tendantoc": "Ê-đê"
	},
	{
		"tendantoc": "Ba na"
	},
	{
		"tendantoc": "Xơ-Đăng"
	},
	{
		"tendantoc": "Sán Chay"
	},
	{
		"tendantoc": "Cơ-ho"
	},
	{
		"tendantoc": "Chăm"
	},
	{
		"tendantoc": "Sán Dìu"
	},
	{
		"tendantoc": "Hrê"
	},
	{
		"tendantoc": "Mnông"
	},
	{
		"tendantoc": "Ra-glai"
	},
	{
		"tendantoc": "Xtiêng"
	},
	{
		"tendantoc": "Bru-Vân Kiều"
	},
	{
		"tendantoc": "Thổ"
	},
	{
		"tendantoc": "Giáy"
	},
	{
		"tendantoc": "Cơ-tu"
	},
	{
		"tendantoc": "Gié Triêng"
	},
	{
		"tendantoc": "Mạ"
	},
	{
		"tendantoc": "Khơ-mú"
	},
	{
		"tendantoc": "Co"
	},
	{
		"tendantoc": "Tà-ôi"
	},
	{
		"tendantoc": "Chơ-ro"
	},
	{
		"tendantoc": "Kháng"
	},
	{
		"tendantoc": "Xinh-mun"
	},
	{
		"tendantoc": "Hà Nhì"
	},
	{
		"tendantoc": "Chu ru"
	},
	{
		"tendantoc": "Lào"
	},
	{
		"tendantoc": "La Chí"
	},
	{
		"tendantoc": "La Ha"
	},
	{
		"tendantoc": "Phù Lá"
	},
	{
		"tendantoc": "La Hủ"
	},
	{
		"tendantoc": "Lự"
	},
	{
		"tendantoc": "Lô Lô"
	},
	{
		"tendantoc": "Chứt"
	},
	{
		"tendantoc": "Mảng"
	},
	{
		"tendantoc": "Pà Thẻn"
	},
	{
		"tendantoc": "Co Lao"
	},
	{
		"tendantoc": "Cống"
	},
	{
		"tendantoc": "Bố Y"
	},
	{
		"tendantoc": "Si La"
	},
	{
		"tendantoc": "Pu Péo"
	},
	{
		"tendantoc": "Brâu"
	},
	{
		"tendantoc": "Ơ Đu"
	},
	{
		"tendantoc": "Rơ măm"
	}
]